FlowCytometry/__init__.py
FlowCytometry/_version.py
FlowCytometry/directories.py
FlowCytometry/flow_cytometer.py
FlowCytometry/gaussian_pulse.py
FlowCytometry/peak.py
FlowCytometry/pulse_analyzer.py
FlowCytometry/utils.py
FlowCytometry/__pycache__/__init__.cpython-311.pyc
FlowCytometry/__pycache__/_version.cpython-311.pyc
FlowCytometry/__pycache__/flow_cytometer.cpython-311.pyc
FlowCytometry/__pycache__/gaussian_pulse.cpython-311.pyc
FlowCytometry/__pycache__/pulse_analyzer.cpython-311.pyc
FlowCytometry-0.0.3.post0.dist-info/LICENSE
FlowCytometry-0.0.3.post0.dist-info/METADATA
FlowCytometry-0.0.3.post0.dist-info/WHEEL
FlowCytometry-0.0.3.post0.dist-info/top_level.txt
FlowCytometry-0.0.3.post0.dist-info/RECORD
